<?xml version="1.0" encoding="utf-8"?><DEFECTS><DEFECT>
    <SFA>
      <FILEPATH>E:\Serpa\UFSC\Prog3\Battle Sea\Battle Sea\</FILEPATH>
      <FILENAME>Enemy.cpp</FILENAME>
      <LINE>6</LINE>
      <COLUMN>11</COLUMN>
    </SFA>
    <DEFECTCODE>26812</DEFECTCODE>
    <DESCRIPTION>The enum type 'Direction' is unscoped. Prefer 'enum class' over 'enum' (Enum.3).</DESCRIPTION>
    <FUNCTION>Enemy::initVariables</FUNCTION>
    <DECORATED>?initVariables@Enemy@@IAEXXZ</DECORATED>
    <FUNCLINE>4</FUNCLINE>
    <PATH></PATH>
  </DEFECT><DEFECT>
    <SFA>
      <FILEPATH>E:\Serpa\UFSC\Prog3\Battle Sea\Battle Sea\</FILEPATH>
      <FILENAME>Player.cpp</FILENAME>
      <LINE>6</LINE>
      <COLUMN>11</COLUMN>
    </SFA>
    <DEFECTCODE>26812</DEFECTCODE>
    <DESCRIPTION>The enum type 'Direction' is unscoped. Prefer 'enum class' over 'enum' (Enum.3).</DESCRIPTION>
    <FUNCTION>Player::initVariables</FUNCTION>
    <DECORATED>?initVariables@Player@@IAEXXZ</DECORATED>
    <FUNCLINE>4</FUNCLINE>
    <PATH></PATH>
  </DEFECT><DEFECT>
    <SFA>
      <FILEPATH>E:\Serpa\UFSC\Prog3\Battle Sea\Battle Sea\</FILEPATH>
      <FILENAME>Player2.cpp</FILENAME>
      <LINE>36</LINE>
      <COLUMN>12</COLUMN>
    </SFA>
    <DEFECTCODE>26812</DEFECTCODE>
    <DESCRIPTION>The enum type 'Direction' is unscoped. Prefer 'enum class' over 'enum' (Enum.3).</DESCRIPTION>
    <FUNCTION>Player2::updateInput</FUNCTION>
    <DECORATED>?updateInput@Player2@@UAEXXZ</DECORATED>
    <FUNCLINE>30</FUNCLINE>
    <PATH></PATH>
  </DEFECT><DEFECT>
    <SFA>
      <FILEPATH>E:\Serpa\UFSC\Prog3\Battle Sea\Battle Sea\</FILEPATH>
      <FILENAME>Submarine.cpp</FILENAME>
      <LINE>3</LINE>
      <COLUMN>11</COLUMN>
    </SFA>
    <DEFECTCODE>26495</DEFECTCODE>
    <DESCRIPTION>Variable 'Submarine::dir' is uninitialized. Always initialize a member variable (type.6).</DESCRIPTION>
    <FUNCTION>Submarine::{ctor}</FUNCTION>
    <DECORATED>??0Submarine@@QAE@XZ</DECORATED>
    <FUNCLINE>3</FUNCLINE>
    <ADDITIONALINFO>
      <targetSymbol>Submarine::dir</targetSymbol>
    </ADDITIONALINFO>
    <PATH></PATH>
  </DEFECT></DEFECTS>